LICENSE
MANIFEST.in
README.rst
setup.py
django_tabular_permissions.egg-info/PKG-INFO
django_tabular_permissions.egg-info/SOURCES.txt
django_tabular_permissions.egg-info/dependency_links.txt
django_tabular_permissions.egg-info/top_level.txt
tabular_permissions/__init__.py
tabular_permissions/admin.py
tabular_permissions/app_settings.py
tabular_permissions/helpers.py
tabular_permissions/widgets.py
tabular_permissions/locale/ar/LC_MESSAGES/django.mo
tabular_permissions/locale/ar/LC_MESSAGES/django.po
tabular_permissions/static/tabular_permissions/tabular_permissions.js
tabular_permissions/templates/tabular_permissions/admin/tabular_permissions.html